obslib/__init__.py
obslib/__main__.py
obslib/exception.py
obslib/obslib.py
obslib-0.7.1.dist-info/licenses/LICENSE
obslib-0.7.1.dist-info/METADATA
obslib-0.7.1.dist-info/WHEEL
obslib-0.7.1.dist-info/top_level.txt
obslib-0.7.1.dist-info/RECORD
