Metadata-Version: 2.4
Name: obslib
Version: 0.7.1
Summary: Object Based Specification Library
Home-page: https://github.com/archmachina/obslib
Download-URL: https://pypi.org/project/obslib/
Author: Jesse Reichman
License: MIT
Keywords: Object,Specification,Library,yaml,json
License-File: LICENSE
Requires-Dist: PyYAML>=6.0.0
Requires-Dist: Jinja2>=3.1.0
Dynamic: author
Dynamic: description-content-type
Dynamic: download-url
Dynamic: home-page
Dynamic: keywords
Dynamic: license
Dynamic: license-file
Dynamic: requires-dist
Dynamic: summary
